.gitignore
.travis.yml
CHANGELOG.rst
CONTRIBUTING.rst
LICENSE
MANIFEST.in
README.rst
RELEASE.rst
setup.py
tox.ini
doc/conf.py
doc/index.rst
doc/requirements.txt
doc/start.rst
doc/_static/fedmsg.png
doc/_static/fedmsg.xcf
doc/_static/site.css
doc/_templates/fedmsg-logo.html
doc/_templates/githubedit.html
doc/_templates/page.html
fedmsg.d/base.py
fedmsg.d/endpoints.py
fedmsg.d/relay.py
fedmsg.d/ssl.py
fedmsg_meta_fedora_infrastructure/__init__.py
fedmsg_meta_fedora_infrastructure/anitya.py
fedmsg_meta_fedora_infrastructure/ansible.py
fedmsg_meta_fedora_infrastructure/askbot.py
fedmsg_meta_fedora_infrastructure/autocloud.py
fedmsg_meta_fedora_infrastructure/badges.py
fedmsg_meta_fedora_infrastructure/bodhi.py
fedmsg_meta_fedora_infrastructure/buildsys.py
fedmsg_meta_fedora_infrastructure/bz.py
fedmsg_meta_fedora_infrastructure/centos_ci.py
fedmsg_meta_fedora_infrastructure/compose.py
fedmsg_meta_fedora_infrastructure/compose2.py
fedmsg_meta_fedora_infrastructure/coprs.py
fedmsg_meta_fedora_infrastructure/datanommer.py
fedmsg_meta_fedora_infrastructure/doc_utilities.py
fedmsg_meta_fedora_infrastructure/elections.py
fedmsg_meta_fedora_infrastructure/faf.py
fedmsg_meta_fedora_infrastructure/fas.py
fedmsg_meta_fedora_infrastructure/fasshim.py
fedmsg_meta_fedora_infrastructure/fedimg.py
fedmsg_meta_fedora_infrastructure/fedocal.py
fedmsg_meta_fedora_infrastructure/fedoracollege.py
fedmsg_meta_fedora_infrastructure/fmn.py
fedmsg_meta_fedora_infrastructure/github.py
fedmsg_meta_fedora_infrastructure/greenwave.py
fedmsg_meta_fedora_infrastructure/hotness.py
fedmsg_meta_fedora_infrastructure/infragit.py
fedmsg_meta_fedora_infrastructure/jenkins.py
fedmsg_meta_fedora_infrastructure/karma.py
fedmsg_meta_fedora_infrastructure/kerneltest.py
fedmsg_meta_fedora_infrastructure/koschei.py
fedmsg_meta_fedora_infrastructure/mailman3.py
fedmsg_meta_fedora_infrastructure/mbs.py
fedmsg_meta_fedora_infrastructure/mdapi.py
fedmsg_meta_fedora_infrastructure/mediawiki.py
fedmsg_meta_fedora_infrastructure.egg-info/PKG-INFO
fedmsg_meta_fedora_infrastructure.egg-info/SOURCES.txt
fedmsg_meta_fedora_infrastructure.egg-info/dependency_links.txt
fedmsg_meta_fedora_infrastructure.egg-info/entry_points.txt
fedmsg_meta_fedora_infrastructure.egg-info/not-zip-safe
fedmsg_meta_fedora_infrastructure.egg-info/requires.txt
fedmsg_meta_fedora_infrastructure.egg-info/top_level.txt
