Metadata-Version: 1.0
Name: fedmsg-meta-fedora-infrastructure
Version: 0.31.0
Summary: fedmsg metadata providers for Fedora Infrastructure's deployment
Home-page: https://github.com/fedora-infra/fedmsg_meta_fedora_infrastructure/
Author: Ralph Bean
Author-email: rbean@redhat.com
License: LGPLv2+
Platform: UNKNOWN
